antialiased_cnns/__init__.py
antialiased_cnns/alexnet.py
antialiased_cnns/blurpool.py
antialiased_cnns/densenet.py
antialiased_cnns/mobilenet.py
antialiased_cnns/resnet.py
antialiased_cnns/util.py
antialiased_cnns/vgg.py
antialiased_cnns-0.3.dist-info/LICENSE.md
antialiased_cnns-0.3.dist-info/METADATA
antialiased_cnns-0.3.dist-info/WHEEL
antialiased_cnns-0.3.dist-info/top_level.txt
antialiased_cnns-0.3.dist-info/RECORD
