Metadata-Version: 2.1
Name: antialiased-cnns
Version: 0.3
Summary: Antialiased models and pooling layer from Zhang. Making Convnets Shift-Invariant Again. ICML 2019.
Home-page: https://github.com/adobe/antialiased-cnns
Author: Richard Zhang
Author-email: rizhang@adobe.com
License: UNKNOWN
Platform: UNKNOWN
Classifier: Programming Language :: Python :: 3
Classifier: License :: Other/Proprietary License
Classifier: Operating System :: OS Independent
